web3modal/__init__.py
web3modal/frontend/build/asset-manifest.json
web3modal/frontend/build/favicon.ico
web3modal/frontend/build/index.html
web3modal/frontend/build/logo192.png
web3modal/frontend/build/logo512.png
web3modal/frontend/build/manifest.json
web3modal/frontend/build/robots.txt
web3modal/frontend/build/images/dashboard-preview.png
web3modal/frontend/build/images/portal-preview.png
web3modal/frontend/build/images/templates-preview.png
web3modal/frontend/build/static/css/main.dbf042a9.css
web3modal/frontend/build/static/css/main.dbf042a9.css.map
web3modal/frontend/build/static/js/1092.9a908cea.chunk.js
web3modal/frontend/build/static/js/1092.9a908cea.chunk.js.map
web3modal/frontend/build/static/js/1119.c76cc87d.chunk.js
web3modal/frontend/build/static/js/125.8effbe1c.chunk.js
web3modal/frontend/build/static/js/125.8effbe1c.chunk.js.LICENSE.txt
web3modal/frontend/build/static/js/125.8effbe1c.chunk.js.map
web3modal/frontend/build/static/js/1345.56120d36.chunk.js
web3modal/frontend/build/static/js/1345.56120d36.chunk.js.map
web3modal/frontend/build/static/js/1369.8c26b4f7.chunk.js
web3modal/frontend/build/static/js/1369.8c26b4f7.chunk.js.map
web3modal/frontend/build/static/js/1437.4c375683.chunk.js
web3modal/frontend/build/static/js/1437.4c375683.chunk.js.map
web3modal/frontend/build/static/js/1539.3a7b70e7.chunk.js
web3modal/frontend/build/static/js/1539.3a7b70e7.chunk.js.map
web3modal/frontend/build/static/js/1834.99e72924.chunk.js
web3modal/frontend/build/static/js/1834.99e72924.chunk.js.map
web3modal/frontend/build/static/js/2103.233e4c6c.chunk.js
web3modal/frontend/build/static/js/2103.233e4c6c.chunk.js.map
web3modal/frontend/build/static/js/2328.ff4cd513.chunk.js
web3modal/frontend/build/static/js/2555.55065282.chunk.js
web3modal/frontend/build/static/js/2610.c0b0f009.chunk.js
web3modal/frontend/build/static/js/2756.7c71f7ab.chunk.js
web3modal/frontend/build/static/js/2756.7c71f7ab.chunk.js.map
web3modal/frontend/build/static/js/2772.9cb27c42.chunk.js
st_web3_modal-0.6.0.dist-info/METADATA
st_web3_modal-0.6.0.dist-info/WHEEL
st_web3_modal-0.6.0.dist-info/top_level.txt
st_web3_modal-0.6.0.dist-info/RECORD
